iapa/__init__.py
iapa/classification.py
iapa/classify.py
iapa/preML.py
iapa-0.4.dist-info/LICENSE.txt
iapa-0.4.dist-info/METADATA
iapa-0.4.dist-info/WHEEL
iapa-0.4.dist-info/top_level.txt
iapa-0.4.dist-info/RECORD
