Metadata-Version: 2.1
Name: iapa
Version: 0.4
Summary: Predictive Analytics Library
Home-page: UNKNOWN
Author: Sng Hao Jun
Author-email: snghaojun@outlook.sg
License: MIT
Keywords: predict
Platform: UNKNOWN
Classifier: Development Status :: 2 - Pre-Alpha
Classifier: Intended Audience :: Developers
Classifier: Operating System :: Microsoft :: Windows :: Windows 10
Classifier: License :: OSI Approved :: MIT License
Classifier: Programming Language :: Python :: 3.8
Requires-Dist: numpy
Requires-Dist: scikit-learn
Requires-Dist: pandas
